docx_word_instance_generator/WordGenerator.py
docx_word_instance_generator/WordGeneratorSettings.py
docx_word_instance_generator/__init__.py
docx_word_instance_generator/version.py
docx_word_instance_generator-0.20.3.dist-info/LICENSE.md
docx_word_instance_generator-0.20.3.dist-info/METADATA
docx_word_instance_generator-0.20.3.dist-info/README.md
docx_word_instance_generator-0.20.3.dist-info/WHEEL
docx_word_instance_generator-0.20.3.dist-info/requirements.txt
docx_word_instance_generator-0.20.3.dist-info/setup.py
docx_word_instance_generator-0.20.3.dist-info/top_level.txt
docx_word_instance_generator-0.20.3.dist-info/RECORD
